domsniff.py
domsniff-0.3.dist-info/LICENSE
domsniff-0.3.dist-info/METADATA
domsniff-0.3.dist-info/WHEEL
domsniff-0.3.dist-info/entry_points.txt
domsniff-0.3.dist-info/top_level.txt
domsniff-0.3.dist-info/RECORD
