Metadata-Version: 2.1
Name: domsniff
Version: 0.3
Summary: Passive DNS sniffer for collecting domain names
Home-page: https://github.com/oskar456/domsniff
Author: Ondřej Caletka
Author-email: ondrej@caletka.cz
License: MIT
Platform: UNKNOWN
Classifier: Development Status :: 4 - Beta
Classifier: Environment :: Console
Classifier: Intended Audience :: System Administrators
Classifier: License :: OSI Approved :: MIT License
Classifier: Operating System :: POSIX :: Linux
Classifier: Programming Language :: Python :: 3.5
Classifier: Programming Language :: Python :: 3.6
Classifier: Programming Language :: Python :: 3 :: Only
Classifier: Topic :: Utilities
Requires-Python: >=3.5
Requires-Dist: click
Requires-Dist: dpkt
Requires-Dist: pypcap
